dhrupad_sah_exception_catcher-1.0.4.dist-info/METADATA
dhrupad_sah_exception_catcher-1.0.4.dist-info/WHEEL
dhrupad_sah_exception_catcher-1.0.4.dist-info/entry_points.txt
dhrupad_sah_exception_catcher-1.0.4.dist-info/licenses/LICENSE
exception_catcher/__init__.py
exception_catcher/auto_init.py
exception_catcher/exception_catcher.py
exception_catcher/fastapi_middleware.py
exception_catcher/flask_middleware.py
exception_catcher/types.py
dhrupad_sah_exception_catcher-1.0.4.dist-info/RECORD
