Metadata-Version: 2.1
Name: dhrupad-sah-exception-catcher
Version: 1.0.4
Summary: Automatically catch and report exceptions to Mira Sentinel with rich context and log integration for AI-powered debugging and automatic fix generation
Keywords: exception,error-handling,monitoring,observability,logging,automation,claude,ai-fixing,fastapi,flask,django
Author-Email: Mira Sentinel Team <noreply@example.com>
License: MIT
Classifier: Development Status :: 4 - Beta
Classifier: Intended Audience :: Developers
Classifier: License :: OSI Approved :: MIT License
Classifier: Operating System :: OS Independent
Classifier: Programming Language :: Python :: 3
Classifier: Programming Language :: Python :: 3.8
Classifier: Programming Language :: Python :: 3.9
Classifier: Programming Language :: Python :: 3.10
Classifier: Programming Language :: Python :: 3.11
Classifier: Programming Language :: Python :: 3.12
Classifier: Topic :: Software Development :: Libraries :: Python Modules
Classifier: Topic :: Software Development :: Quality Assurance
Classifier: Topic :: System :: Logging
Classifier: Topic :: System :: Monitoring
Project-URL: Homepage, https://github.com/dhrupad-sah/python-exception-catcher
Project-URL: Repository, https://github.com/dhrupad-sah/python-exception-catcher
Project-URL: Documentation, https://github.com/dhrupad-sah/python-exception-catcher#readme
Project-URL: Issues, https://github.com/dhrupad-sah/python-exception-catcher/issues
Requires-Python: >=3.8
Requires-Dist: httpx>=0.25.0
Requires-Dist: pydantic>=2.0.0
Requires-Dist: psutil>=5.9.0
Provides-Extra: fastapi
Requires-Dist: fastapi>=0.100.0; extra == "fastapi"
Requires-Dist: starlette>=0.27.0; extra == "fastapi"
Provides-Extra: flask
Requires-Dist: flask>=2.0.0; extra == "flask"
Provides-Extra: django
Requires-Dist: django>=4.0.0; extra == "django"
Provides-Extra: dev
Requires-Dist: pytest>=7.0.0; extra == "dev"
Requires-Dist: pytest-asyncio>=0.21.0; extra == "dev"
Requires-Dist: black>=23.0.0; extra == "dev"
Requires-Dist: isort>=5.12.0; extra == "dev"
Requires-Dist: mypy>=1.5.0; extra == "dev"
Requires-Dist: fastapi>=0.100.0; extra == "dev"
Requires-Dist: starlette>=0.27.0; extra == "dev"
Requires-Dist: flask>=2.0.0; extra == "dev"
Requires-Dist: uvicorn>=0.23.0; extra == "dev"
